inquirer3/__init__.py
inquirer3/errors.py
inquirer3/events.py
inquirer3/prompt.py
inquirer3/questions.py
inquirer3/render/__init__.py
inquirer3/render/console/__init__.py
inquirer3/render/console/_checkbox.py
inquirer3/render/console/_confirm.py
inquirer3/render/console/_editor.py
inquirer3/render/console/_list.py
inquirer3/render/console/_other.py
inquirer3/render/console/_password.py
inquirer3/render/console/_path.py
inquirer3/render/console/_text.py
inquirer3/render/console/base.py
inquirer3/shortcuts.py
inquirer3/themes.py
inquirer3-0.6.0.dist-info/LICENSE
inquirer3-0.6.0.dist-info/METADATA
inquirer3-0.6.0.dist-info/WHEEL
inquirer3-0.6.0.dist-info/RECORD
