Metadata-Version: 2.1
Name: inquirer3
Version: 0.6.0
Summary: Collection of common interactive command line user interfaces, based on Inquirer.js
Home-page: https://github.com/guysalt/python-inquirer3
License: MIT
Author: Guy Salton
Author-email: guy123121@gmail.com
Requires-Python: >=3.8.1,<4.0.0
Classifier: Development Status :: 5 - Production/Stable
Classifier: Environment :: Console
Classifier: Intended Audience :: Developers
Classifier: License :: OSI Approved :: MIT License
Classifier: Operating System :: OS Independent
Classifier: Programming Language :: Python :: 3
Classifier: Programming Language :: Python :: 3.9
Classifier: Programming Language :: Python :: 3.10
Classifier: Programming Language :: Python :: 3.11
Classifier: Programming Language :: Python :: 3.12
Classifier: Programming Language :: Python :: 3.8
Classifier: Topic :: Software Development :: Libraries :: Application Frameworks
Classifier: Topic :: Software Development :: User Interfaces
Requires-Dist: blessed (>=1.20.0,<2.0.0)
Requires-Dist: editor (>=1.6.6,<2.0.0)
Requires-Dist: readchar (>=4.0.6,<5.0.0)
Project-URL: Documentation, https://python-inquirer3.readthedocs.io/en/latest/
Project-URL: Repository, https://github.com/guysalt/python-inquirer3
